prometheus_sanic/__init__.py
prometheus_sanic/base.py
prometheus_sanic/constants.py
prometheus_sanic/endpoint.py
prometheus_sanic/exceptions.py
prometheus_sanic/handlers.py
prometheus_sanic/metrics.py
prometheus_sanic-3.0.0.dist-info/LICENSE
prometheus_sanic-3.0.0.dist-info/WHEEL
prometheus_sanic-3.0.0.dist-info/METADATA
prometheus_sanic-3.0.0.dist-info/RECORD
