Metadata-Version: 2.1
Name: prometheus-sanic
Version: 3.0.0
Summary: Exposes Prometheus monitoring metrics of Sanic apps.
Home-page: https://github.com/skar404/prometheus-sanic
License: MIT
Keywords: python,prometheus,sanic,monitoring,python-library
Author: Dan Kruchinin
Author-email: dan.kruchinin@gmail.com
Requires-Python: >=3.7,<4.0
Classifier: Development Status :: 3 - Alpha
Classifier: Environment :: Web Environment
Classifier: Intended Audience :: Developers
Classifier: License :: OSI Approved :: MIT License
Classifier: Operating System :: OS Independent
Classifier: Programming Language :: Python :: 3
Classifier: Programming Language :: Python :: 3.10
Classifier: Programming Language :: Python :: 3.6
Classifier: Programming Language :: Python :: 3.7
Classifier: Programming Language :: Python :: 3.8
Classifier: Programming Language :: Python :: 3.9
Classifier: Topic :: Internet :: WWW/HTTP :: Dynamic Content
Classifier: Topic :: Software Development :: Libraries :: Python Modules
Classifier: Topic :: System :: Monitoring
Requires-Dist: prometheus-client (>=0.7.1,<0.8.0)
Requires-Dist: sanic (>=22.0.0)
Project-URL: Repository, https://github.com/skar404/prometheus-sanic
